LICENSE
README.md
setup.py
saplings/__init__.py
saplings/evaluator.py
saplings/model.py
saplings/prompts.py
saplings.egg-info/PKG-INFO
saplings.egg-info/SOURCES.txt
saplings.egg-info/dependency_links.txt
saplings.egg-info/requires.txt
saplings.egg-info/top_level.txt
saplings/abstract/Evaluator.py
saplings/abstract/Tool.py
saplings/abstract/__init__.py
saplings/agents/AStar.py
saplings/agents/BFS.py
saplings/agents/Base.py
saplings/agents/COT.py
saplings/agents/DFS.py
saplings/agents/Greedy.py
saplings/agents/MonteCarlo.py
saplings/agents/__init__.py
saplings/dtos/Evaluation.py
saplings/dtos/Message.py
saplings/dtos/Node.py
saplings/dtos/ToolCall.py
saplings/dtos/__init__.py
saplings/examples/Addition.py
saplings/examples/Division.py
saplings/examples/Multiplication.py
saplings/examples/Subtraction.py
saplings/examples/__init__.py