Metadata-Version: 2.1
Name: saplings
Version: 6.1.0
Summary: Build smarter AI agents with tree search
Home-page: https://github.com/shobrook/saplings
Author: shobrook
Author-email: shobrookj@gmail.com
License: MIT
Keywords: llm,agent,openai,search-algorithm,search,ai,monte carlo tree search,mcts,a*,greedy
Requires-Python: >=3
License-File: LICENSE
Requires-Dist: json-repair
Requires-Dist: litellm
